{
  "openapi": "3.0.0",
  "info": {
    "title": "Hyperliquid Node API",
    "version": "1.0.0",
    "description": "This is an API for interacting with Hyperliquid."
  },
  "servers": [
    {
      "url": "https://api.hyperliquid.xyz"
    }
  ],
  "paths": {
    "/info": {
      "post": {
        "tags": [
          "hyperliquid operations"
        ],
        "summary": "info (gossipRootIps)",
        "operationId": "infoGossipRootIps",
        "requestBody": {
          "required": true,
          "content": {
            "application/json": {
              "schema": {
                "type": "object",
                "properties": {
                  "type": {
                    "type": "string",
                    "default": "gossipRootIps",
                    "enum": ["gossipRootIps"]
                  }
                },
                "required": [
                  "type"
                ]
              }
            }
          }
        },
        "responses": {
          "200": {
            "description": "Successful response",
            "content": {
              "application/json": {
                "schema": {
                  "type": "array",
                  "items": {
                    "type": "string"
                  }
                }
              }
            }
          }
        }
      }
    }
  },
  "x-readme": {
    "explorer-enabled": true,
    "proxy-enabled": true
  }
}